poetry_plugin_check_yanked/__init__.py
poetry_plugin_check_yanked/command.py
poetry_plugin_check_yanked/plugin.py
poetry_plugin_check_yanked/status.py
poetry_plugin_check_yanked-0.3.0.dist-info/LICENSE.txt
poetry_plugin_check_yanked-0.3.0.dist-info/METADATA
poetry_plugin_check_yanked-0.3.0.dist-info/WHEEL
poetry_plugin_check_yanked-0.3.0.dist-info/entry_points.txt
poetry_plugin_check_yanked-0.3.0.dist-info/RECORD
