Metadata-Version: 2.1
Name: poetry-plugin-check-yanked
Version: 0.3.0
Summary: A Poetry plugin to check for 'yanked' packages in the poetry.lock file.
Home-page: https://github.com/seapagan/poetry-plugin-check-yanked
License: MIT
Author: Grant Ramsay
Author-email: seapagan@gmail.com
Requires-Python: >=3.9,<4.0
Classifier: Development Status :: 4 - Beta
Classifier: Environment :: Plugins
Classifier: Intended Audience :: Developers
Classifier: License :: OSI Approved :: MIT License
Classifier: Operating System :: OS Independent
Classifier: Programming Language :: Python :: 3
Classifier: Programming Language :: Python :: 3.9
Classifier: Programming Language :: Python :: 3.10
Classifier: Programming Language :: Python :: 3.11
Classifier: Programming Language :: Python :: 3.12
Classifier: Topic :: Software Development
Classifier: Topic :: Software Development :: Libraries
Classifier: Topic :: Utilities
Requires-Dist: pickledb (>=0.9.2,<0.10.0)
Requires-Dist: platformdirs (>=4.2.2,<5.0.0)
Requires-Dist: poetry (>=1.6.0)
Requires-Dist: requests (>=2.32.3,<3.0.0)
Requires-Dist: rtoml (>=0.10.0)
Project-URL: Bug Tracker, https://github.com/seapagan/poetry-plugin-check-yanked/issues
Project-URL: Changelog, https://github.com/seapagan/poetry-plugin-check-yanked/blob/main/CHANGELOG.md
Project-URL: Pull Requests, https://github.com/seapagan/poetry-plugin-check-yanked/pulls
Project-URL: Repository, https://github.com/seapagan/poetry-plugin-check-yanked
